Metadata-Version: 1.0
Name: mmal-proto
Version: 0.0.1
Summary: Meteorological Middleware Application Layer protobuf bindings
Home-page: https://github.com/hodgesds/mmbal-proto/python
Author: Daniel Hodges
Author-email: hodges.daniel.scott@gmail.com
License: UNKNOWN
Platform: UNKNOWN
